klayout_pyxs/__init__.py
klayout_pyxs/compat.py
klayout_pyxs/geometry_2d.py
klayout_pyxs/geometry_3d.py
klayout_pyxs/layer_parameters.py
klayout_pyxs/pyxs3D_lib.py
klayout_pyxs/pyxs_lib.py
klayout_pyxs/utils.py
klayout_pyxs-0.1.13.dist-info/LICENSE
klayout_pyxs-0.1.13.dist-info/METADATA
klayout_pyxs-0.1.13.dist-info/WHEEL
klayout_pyxs-0.1.13.dist-info/top_level.txt
klayout_pyxs-0.1.13.dist-info/RECORD
