Metadata-Version: 2.1
Name: klayout-pyxs
Version: 0.1.13
Summary: python port of the Klayout xsection project
Home-page: https://github.com/dimapu/klayout_pyxs
Author: Dima Pustakhod
License: MIT
Platform: UNKNOWN
Classifier: Programming Language :: Python
Requires-Python: >=3.6
License-File: LICENSE
